[{"Timestamp":1780779380,"DateTimeStr":"2026-06-07 04:56:20","Direction":"定位→反位","Duration":9.16,"SampleInterval":0.04,"SampleCount":229,"CurrentA":[],"CurrentB":[],"CurrentC":[],"Power":[]},{"Timestamp":1780784339,"DateTimeStr":"2026-06-07 06:18:59","Direction":"反位→定位","Duration":9.24,"SampleInterval":0.04,"SampleCount":231,"CurrentA":[],"CurrentB":[],"CurrentC":[],"Power":[]},{"Timestamp":1780801635,"DateTimeStr":"2026-06-07 11:07:15","Direction":"定位→反位","Duration":9.2,"SampleInterval":0.04,"SampleCount":230,"CurrentA":[],"CurrentB":[],"CurrentC":[],"Power":[]},{"Timestamp":1780802721,"DateTimeStr":"2026-06-07 11:25:21","Direction":"反位→定位","Duration":9.32,"SampleInterval":0.04,"SampleCount":233,"CurrentA":[],"CurrentB":[],"CurrentC":[],"Power":[]},{"Timestamp":1780815425,"DateTimeStr":"2026-06-07 14:57:05","Direction":"定位→反位","Duration":9.24,"SampleInterval":0.04,"SampleCount":231,"CurrentA":[],"CurrentB":[],"CurrentC":[],"Power":[]},{"Timestamp":1780815632,"DateTimeStr":"2026-06-07 15:00:32","Direction":"反位→定位","Duration":9.32,"SampleInterval":0.04,"SampleCount":233,"CurrentA":[],"CurrentB":[],"CurrentC":[],"Power":[]},{"Timestamp":1780821139,"DateTimeStr":"2026-06-07 16:32:19","Direction":"定位→反位","Duration":9.16,"SampleInterval":0.04,"SampleCount":229,"CurrentA":[],"CurrentB":[],"CurrentC":[],"Power":[]},{"Timestamp":1780823205,"DateTimeStr":"2026-06-07 17:06:45","Direction":"反位→定位","Duration":9.28,"SampleInterval":0.04,"SampleCount":232,"CurrentA":[],"CurrentB":[],"CurrentC":[],"Power":[]}]