[{"Timestamp":1780692979,"DateTimeStr":"2026-06-06 04:56:19","Direction":"定位→反位","Duration":9.2,"SampleInterval":0.04,"SampleCount":230,"CurrentA":[],"CurrentB":[],"CurrentC":[],"Power":[]},{"Timestamp":1780697962,"DateTimeStr":"2026-06-06 06:19:22","Direction":"反位→定位","Duration":9.24,"SampleInterval":0.04,"SampleCount":231,"CurrentA":[],"CurrentB":[],"CurrentC":[],"Power":[]},{"Timestamp":1780715112,"DateTimeStr":"2026-06-06 11:05:12","Direction":"定位→反位","Duration":9.2,"SampleInterval":0.04,"SampleCount":230,"CurrentA":[],"CurrentB":[],"CurrentC":[],"Power":[]},{"Timestamp":1780716311,"DateTimeStr":"2026-06-06 11:25:11","Direction":"反位→定位","Duration":9.28,"SampleInterval":0.04,"SampleCount":232,"CurrentA":[],"CurrentB":[],"CurrentC":[],"Power":[]},{"Timestamp":1780728992,"DateTimeStr":"2026-06-06 14:56:32","Direction":"定位→反位","Duration":9.2,"SampleInterval":0.04,"SampleCount":230,"CurrentA":[],"CurrentB":[],"CurrentC":[],"Power":[]},{"Timestamp":1780729203,"DateTimeStr":"2026-06-06 15:00:03","Direction":"反位→定位","Duration":9.24,"SampleInterval":0.04,"SampleCount":231,"CurrentA":[],"CurrentB":[],"CurrentC":[],"Power":[]},{"Timestamp":1780734772,"DateTimeStr":"2026-06-06 16:32:52","Direction":"定位→反位","Duration":9.24,"SampleInterval":0.04,"SampleCount":231,"CurrentA":[],"CurrentB":[],"CurrentC":[],"Power":[]},{"Timestamp":1780736852,"DateTimeStr":"2026-06-06 17:07:32","Direction":"反位→定位","Duration":9.28,"SampleInterval":0.04,"SampleCount":232,"CurrentA":[],"CurrentB":[],"CurrentC":[],"Power":[]}]