[{"Timestamp":1766696174,"DateTimeStr":"2025-12-26 04:56:14","Direction":"定位→反位","Duration":8.88,"SampleInterval":0.04,"SampleCount":222,"CurrentA":[],"CurrentB":[],"CurrentC":[],"Power":[]},{"Timestamp":1766700653,"DateTimeStr":"2025-12-26 06:10:53","Direction":"反位→定位","Duration":8.84,"SampleInterval":0.04,"SampleCount":221,"CurrentA":[],"CurrentB":[],"CurrentC":[],"Power":[]},{"Timestamp":1766701003,"DateTimeStr":"2025-12-26 06:16:43","Direction":"定位→反位","Duration":8.92,"SampleInterval":0.04,"SampleCount":223,"CurrentA":[],"CurrentB":[],"CurrentC":[],"Power":[]},{"Timestamp":1766704721,"DateTimeStr":"2025-12-26 07:18:41","Direction":"反位→定位","Duration":8.88,"SampleInterval":0.04,"SampleCount":222,"CurrentA":[],"CurrentB":[],"CurrentC":[],"Power":[]},{"Timestamp":1766708384,"DateTimeStr":"2025-12-26 08:19:44","Direction":"定位→反位","Duration":8.88,"SampleInterval":0.04,"SampleCount":222,"CurrentA":[],"CurrentB":[],"CurrentC":[],"Power":[]},{"Timestamp":1766710459,"DateTimeStr":"2025-12-26 08:54:19","Direction":"反位→定位","Duration":8.8,"SampleInterval":0.04,"SampleCount":220,"CurrentA":[],"CurrentB":[],"CurrentC":[],"Power":[]},{"Timestamp":1766716515,"DateTimeStr":"2025-12-26 10:35:15","Direction":"定位→反位","Duration":8.84,"SampleInterval":0.04,"SampleCount":221,"CurrentA":[],"CurrentB":[],"CurrentC":[],"Power":[]},{"Timestamp":1766718313,"DateTimeStr":"2025-12-26 11:05:13","Direction":"反位→定位","Duration":8.8,"SampleInterval":0.04,"SampleCount":220,"CurrentA":[],"CurrentB":[],"CurrentC":[],"Power":[]},{"Timestamp":1766718634,"DateTimeStr":"2025-12-26 11:10:34","Direction":"定位→反位","Duration":8.8,"SampleInterval":0.04,"SampleCount":220,"CurrentA":[],"CurrentB":[],"CurrentC":[],"Power":[]},{"Timestamp":1766720672,"DateTimeStr":"2025-12-26 11:44:32","Direction":"反位→定位","Duration":8.84,"SampleInterval":0.04,"SampleCount":221,"CurrentA":[],"CurrentB":[],"CurrentC":[],"Power":[]},{"Timestamp":1766731460,"DateTimeStr":"2025-12-26 14:44:20","Direction":"定位→反位","Duration":8.84,"SampleInterval":0.04,"SampleCount":221,"CurrentA":[],"CurrentB":[],"CurrentC":[],"Power":[]},{"Timestamp":1766732627,"DateTimeStr":"2025-12-26 15:03:47","Direction":"反位→定位","Duration":8.8,"SampleInterval":0.04,"SampleCount":220,"CurrentA":[],"CurrentB":[],"CurrentC":[],"Power":[]},{"Timestamp":1766733216,"DateTimeStr":"2025-12-26 15:13:36","Direction":"定位→反位","Duration":8.88,"SampleInterval":0.04,"SampleCount":222,"CurrentA":[],"CurrentB":[],"CurrentC":[],"Power":[]},{"Timestamp":1766734920,"DateTimeStr":"2025-12-26 15:42:00","Direction":"反位→定位","Duration":8.8,"SampleInterval":0.04,"SampleCount":220,"CurrentA":[],"CurrentB":[],"CurrentC":[],"Power":[]},{"Timestamp":1766738330,"DateTimeStr":"2025-12-26 16:38:50","Direction":"定位→反位","Duration":8.92,"SampleInterval":0.04,"SampleCount":223,"CurrentA":[],"CurrentB":[],"CurrentC":[],"Power":[]},{"Timestamp":1766740738,"DateTimeStr":"2025-12-26 17:18:58","Direction":"反位→定位","Duration":8.8,"SampleInterval":0.04,"SampleCount":220,"CurrentA":[],"CurrentB":[],"CurrentC":[],"Power":[]}]