[{"Timestamp":1780779380,"DateTimeStr":"2026-06-07 04:56:20","Direction":"定位→反位","Duration":8.8,"SampleInterval":0.04,"SampleCount":220,"CurrentA":[],"CurrentB":[],"CurrentC":[],"Power":[]},{"Timestamp":1780783843,"DateTimeStr":"2026-06-07 06:10:43","Direction":"反位→定位","Duration":8.84,"SampleInterval":0.04,"SampleCount":221,"CurrentA":[],"CurrentB":[],"CurrentC":[],"Power":[]},{"Timestamp":1780784178,"DateTimeStr":"2026-06-07 06:16:18","Direction":"定位→反位","Duration":8.84,"SampleInterval":0.04,"SampleCount":221,"CurrentA":[],"CurrentB":[],"CurrentC":[],"Power":[]},{"Timestamp":1780787898,"DateTimeStr":"2026-06-07 07:18:18","Direction":"反位→定位","Duration":8.88,"SampleInterval":0.04,"SampleCount":222,"CurrentA":[],"CurrentB":[],"CurrentC":[],"Power":[]},{"Timestamp":1780801635,"DateTimeStr":"2026-06-07 11:07:15","Direction":"定位→反位","Duration":8.84,"SampleInterval":0.04,"SampleCount":221,"CurrentA":[],"CurrentB":[],"CurrentC":[],"Power":[]},{"Timestamp":1780802364,"DateTimeStr":"2026-06-07 11:19:24","Direction":"反位→定位","Duration":8.88,"SampleInterval":0.04,"SampleCount":222,"CurrentA":[],"CurrentB":[],"CurrentC":[],"Power":[]},{"Timestamp":1780815175,"DateTimeStr":"2026-06-07 14:52:55","Direction":"定位→反位","Duration":8.84,"SampleInterval":0.04,"SampleCount":221,"CurrentA":[],"CurrentB":[],"CurrentC":[],"Power":[]},{"Timestamp":1780817669,"DateTimeStr":"2026-06-07 15:34:29","Direction":"反位→定位","Duration":8.88,"SampleInterval":0.04,"SampleCount":222,"CurrentA":[],"CurrentB":[],"CurrentC":[],"Power":[]},{"Timestamp":1780821139,"DateTimeStr":"2026-06-07 16:32:19","Direction":"定位→反位","Duration":8.84,"SampleInterval":0.04,"SampleCount":221,"CurrentA":[],"CurrentB":[],"CurrentC":[],"Power":[]},{"Timestamp":1780822840,"DateTimeStr":"2026-06-07 17:00:40","Direction":"反位→定位","Duration":8.88,"SampleInterval":0.04,"SampleCount":222,"CurrentA":[],"CurrentB":[],"CurrentC":[],"Power":[]}]