[{"Timestamp":1765213791,"DateTimeStr":"2025-12-09 01:09:51","Direction":"定位→反位","Duration":9.12,"SampleInterval":0.04,"SampleCount":228,"CurrentA":[],"CurrentB":[],"CurrentC":[],"Power":[]},{"Timestamp":1765215568,"DateTimeStr":"2025-12-09 01:39:28","Direction":"反位→定位","Duration":8.96,"SampleInterval":0.04,"SampleCount":224,"CurrentA":[],"CurrentB":[],"CurrentC":[],"Power":[]},{"Timestamp":1765219097,"DateTimeStr":"2025-12-09 02:38:17","Direction":"定位→反位","Duration":9.12,"SampleInterval":0.04,"SampleCount":228,"CurrentA":[],"CurrentB":[],"CurrentC":[],"Power":[]},{"Timestamp":1765219418,"DateTimeStr":"2025-12-09 02:43:38","Direction":"反位→定位","Duration":9,"SampleInterval":0.04,"SampleCount":225,"CurrentA":[],"CurrentB":[],"CurrentC":[],"Power":[]},{"Timestamp":1765219456,"DateTimeStr":"2025-12-09 02:44:16","Direction":"定位→反位","Duration":31.64,"SampleInterval":0.04,"SampleCount":791,"CurrentA":[],"CurrentB":[],"CurrentC":[],"Power":[]},{"Timestamp":1765219513,"DateTimeStr":"2025-12-09 02:45:13","Direction":"反位→定位","Duration":31.6,"SampleInterval":0.04,"SampleCount":790,"CurrentA":[],"CurrentB":[],"CurrentC":[],"Power":[]},{"Timestamp":1765219566,"DateTimeStr":"2025-12-09 02:46:06","Direction":"定位→反位","Duration":8.32,"SampleInterval":0.04,"SampleCount":208,"CurrentA":[],"CurrentB":[],"CurrentC":[],"Power":[]},{"Timestamp":1765219680,"DateTimeStr":"2025-12-09 02:48:00","Direction":"反位→定位","Duration":8.96,"SampleInterval":0.04,"SampleCount":224,"CurrentA":[],"CurrentB":[],"CurrentC":[],"Power":[]},{"Timestamp":1765220154,"DateTimeStr":"2025-12-09 02:55:54","Direction":"定位→反位","Duration":9.08,"SampleInterval":0.04,"SampleCount":227,"CurrentA":[],"CurrentB":[],"CurrentC":[],"Power":[]},{"Timestamp":1765220389,"DateTimeStr":"2025-12-09 02:59:49","Direction":"反位→定位","Duration":9,"SampleInterval":0.04,"SampleCount":225,"CurrentA":[],"CurrentB":[],"CurrentC":[],"Power":[]},{"Timestamp":1765234152,"DateTimeStr":"2025-12-09 06:49:12","Direction":"定位→反位","Duration":9.12,"SampleInterval":0.04,"SampleCount":228,"CurrentA":[],"CurrentB":[],"CurrentC":[],"Power":[]},{"Timestamp":1765234577,"DateTimeStr":"2025-12-09 06:56:17","Direction":"反位→定位","Duration":8.96,"SampleInterval":0.04,"SampleCount":224,"CurrentA":[],"CurrentB":[],"CurrentC":[],"Power":[]},{"Timestamp":1765237037,"DateTimeStr":"2025-12-09 07:37:17","Direction":"定位→反位","Duration":9.12,"SampleInterval":0.04,"SampleCount":228,"CurrentA":[],"CurrentB":[],"CurrentC":[],"Power":[]},{"Timestamp":1765244886,"DateTimeStr":"2025-12-09 09:48:06","Direction":"反位→定位","Duration":9.04,"SampleInterval":0.04,"SampleCount":226,"CurrentA":[],"CurrentB":[],"CurrentC":[],"Power":[]},{"Timestamp":1765245894,"DateTimeStr":"2025-12-09 10:04:54","Direction":"定位→反位","Duration":9.16,"SampleInterval":0.04,"SampleCount":229,"CurrentA":[],"CurrentB":[],"CurrentC":[],"Power":[]},{"Timestamp":1765251485,"DateTimeStr":"2025-12-09 11:38:05","Direction":"反位→定位","Duration":8.96,"SampleInterval":0.04,"SampleCount":224,"CurrentA":[],"CurrentB":[],"CurrentC":[],"Power":[]},{"Timestamp":1765254171,"DateTimeStr":"2025-12-09 12:22:51","Direction":"定位→反位","Duration":9.12,"SampleInterval":0.04,"SampleCount":228,"CurrentA":[],"CurrentB":[],"CurrentC":[],"Power":[]},{"Timestamp":1765268815,"DateTimeStr":"2025-12-09 16:26:55","Direction":"反位→定位","Duration":9,"SampleInterval":0.04,"SampleCount":225,"CurrentA":[],"CurrentB":[],"CurrentC":[],"Power":[]},{"Timestamp":1765270800,"DateTimeStr":"2025-12-09 17:00:00","Direction":"定位→反位","Duration":9.12,"SampleInterval":0.04,"SampleCount":228,"CurrentA":[],"CurrentB":[],"CurrentC":[],"Power":[]},{"Timestamp":1765273508,"DateTimeStr":"2025-12-09 17:45:08","Direction":"反位→定位","Duration":8.96,"SampleInterval":0.04,"SampleCount":224,"CurrentA":[],"CurrentB":[],"CurrentC":[],"Power":[]},{"Timestamp":1765276085,"DateTimeStr":"2025-12-09 18:28:05","Direction":"定位→反位","Duration":9.12,"SampleInterval":0.04,"SampleCount":228,"CurrentA":[],"CurrentB":[],"CurrentC":[],"Power":[]},{"Timestamp":1765293703,"DateTimeStr":"2025-12-09 23:21:43","Direction":"反位→定位","Duration":9.04,"SampleInterval":0.04,"SampleCount":226,"CurrentA":[],"CurrentB":[],"CurrentC":[],"Power":[]}]