[{"Timestamp":1766875767,"DateTimeStr":"2025-12-28 06:49:27","Direction":"定位→反位","Duration":9.12,"SampleInterval":0.04,"SampleCount":228,"CurrentA":[],"CurrentB":[],"CurrentC":[],"Power":[]},{"Timestamp":1766876177,"DateTimeStr":"2025-12-28 06:56:17","Direction":"反位→定位","Duration":9.04,"SampleInterval":0.04,"SampleCount":226,"CurrentA":[],"CurrentB":[],"CurrentC":[],"Power":[]},{"Timestamp":1766878513,"DateTimeStr":"2025-12-28 07:35:13","Direction":"定位→反位","Duration":9.12,"SampleInterval":0.04,"SampleCount":228,"CurrentA":[],"CurrentB":[],"CurrentC":[],"Power":[]},{"Timestamp":1766886493,"DateTimeStr":"2025-12-28 09:48:13","Direction":"反位→定位","Duration":9,"SampleInterval":0.04,"SampleCount":225,"CurrentA":[],"CurrentB":[],"CurrentC":[],"Power":[]},{"Timestamp":1766887521,"DateTimeStr":"2025-12-28 10:05:21","Direction":"定位→反位","Duration":9.08,"SampleInterval":0.04,"SampleCount":227,"CurrentA":[],"CurrentB":[],"CurrentC":[],"Power":[]},{"Timestamp":1766893158,"DateTimeStr":"2025-12-28 11:39:18","Direction":"反位→定位","Duration":9,"SampleInterval":0.04,"SampleCount":225,"CurrentA":[],"CurrentB":[],"CurrentC":[],"Power":[]},{"Timestamp":1766895670,"DateTimeStr":"2025-12-28 12:21:10","Direction":"定位→反位","Duration":9.12,"SampleInterval":0.04,"SampleCount":228,"CurrentA":[],"CurrentB":[],"CurrentC":[],"Power":[]},{"Timestamp":1766910456,"DateTimeStr":"2025-12-28 16:27:36","Direction":"反位→定位","Duration":9,"SampleInterval":0.04,"SampleCount":225,"CurrentA":[],"CurrentB":[],"CurrentC":[],"Power":[]},{"Timestamp":1766912431,"DateTimeStr":"2025-12-28 17:00:31","Direction":"定位→反位","Duration":9.12,"SampleInterval":0.04,"SampleCount":228,"CurrentA":[],"CurrentB":[],"CurrentC":[],"Power":[]},{"Timestamp":1766915113,"DateTimeStr":"2025-12-28 17:45:13","Direction":"反位→定位","Duration":8.96,"SampleInterval":0.04,"SampleCount":224,"CurrentA":[],"CurrentB":[],"CurrentC":[],"Power":[]},{"Timestamp":1766917761,"DateTimeStr":"2025-12-28 18:29:21","Direction":"定位→反位","Duration":9.16,"SampleInterval":0.04,"SampleCount":229,"CurrentA":[],"CurrentB":[],"CurrentC":[],"Power":[]},{"Timestamp":1766935321,"DateTimeStr":"2025-12-28 23:22:01","Direction":"反位→定位","Duration":9,"SampleInterval":0.04,"SampleCount":225,"CurrentA":[],"CurrentB":[],"CurrentC":[],"Power":[]}]